<?xml version="1.0" encoding="utf-8"?>
<search>
  
  
  
  <entry>
    <title>博客寫作計畫</title>
    <link href="/2020/%E5%8D%9A%E5%AE%A2%E5%AF%AB%E4%BD%9C%E8%A8%88%E7%95%AB/"/>
    <url>/2020/%E5%8D%9A%E5%AE%A2%E5%AF%AB%E4%BD%9C%E8%A8%88%E7%95%AB/</url>
    
    <content type="html"><![CDATA[<p>目前的计划是这样的,</p><p>在三月写完有关向量和矩阵的, 如果有时间我会把以前我写的 lambda calculus 改好也放上来,</p><p>四月可能比较忙, 我估计只能在课余时间复习一下微积分</p><p>五月会更忙一点, 如果有时间的话我会开始写微积分的内容</p><p>六月应该花一周就能写完关于微积分的内容, 之后的时间我可能在学习搭网站, 没准我会搬离github自己搭一个服务器什么的, 这样我就可以容纳更多的功能</p><p>七月份的话我觉得可以写点关于数学建模的文章, 我也对electron 和 ionic 框架感兴趣, 目前对学习这两个框架需要的精力没什么概念,</p><p>所以计划大概就截止到七月份 剩下的以后再说</p>]]></content>
    
    
    
    <tags>
      
      <tag>uncategorised</tag>
      
    </tags>
    
  </entry>
  
  
  
  <entry>
    <title>A Review of Vector</title>
    <link href="/2020/A-Review-of-Vector/"/>
    <url>/2020/A-Review-of-Vector/</url>
    
    <content type="html"><![CDATA[<h1 id="a-review-of-vector"><a class="markdownIt-Anchor" href="#a-review-of-vector"></a> A Review of Vector</h1><p>In this post we will go over the basic operation toward vector.</p><h3 id="what-is-a-vector"><a class="markdownIt-Anchor" href="#what-is-a-vector"></a> What is a vector</h3><p>In the reallife, we do not always only want to look at the magnitude of a value, but  sometimes we also need to concern about the direction of a value. For example, a boat in a river.</p><p><img src="/Users/tony/Downloads/IMG_3969DC6A76B6-1.jpeg" srcset="/img/loading.gif" alt="IMG_3969DC6A76B6-1" /></p><p>We can use a group of numbers to denote a vector. For example (x, y) or (x, y, z).</p><h3 id="zero-vector"><a class="markdownIt-Anchor" href="#zero-vector"></a> Zero vector</h3><p>Some vectors has “strange” behaviour.</p><p>We prescribe zero vectors, (a<sub>1</sub>, a<sub>2</sub>, a<sub>3</sub>, … , a<sub>n</sub>) where a<sub>1</sub> = a<sub>2</sub> =  a<sub>3</sub> = … = a<sub>n</sub> = 0 and n <span class="katex"><span class="katex-mathml"><math><semantics><mrow><mo>∈</mo><msup><mi mathvariant="double-struck">N</mi><mo>∗</mo></msup></mrow><annotation encoding="application/x-tex">\in \N ^*</annotation></semantics></math></span><span class="katex-html" aria-hidden="true"><span class="base"><span class="strut" style="height:0.5782em;vertical-align:-0.0391em;"></span><span class="mrel">∈</span><span class="mspace" style="margin-right:0.2777777777777778em;"></span></span><span class="base"><span class="strut" style="height:0.68889em;vertical-align:0em;"></span><span class="mord"><span class="mord"><span class="mord mathbb">N</span></span><span class="msupsub"><span class="vlist-t"><span class="vlist-r"><span class="vlist" style="height:0.688696em;"><span style="top:-3.063em;margin-right:0.05em;"><span class="pstrut" style="height:2.7em;"></span><span class="sizing reset-size6 size3 mtight"><span class="mbin mtight">∗</span></span></span></span></span></span></span></span></span></span></span>, are parallel to any vectors. And all the zero vectors are equal, meaning (0, 0) is treated as the same as (0, 0, 0).</p><p>The definition of zero vector is just for convenience. And it is intuitive. All the vectors pointing to no direction and has no magnitude are the same.</p><p>这部分我有点忘了, 可能不是这样的.</p><h3 id="vector-addition"><a class="markdownIt-Anchor" href="#vector-addition"></a> Vector addition</h3><p>We can only add the vectors in the same dimension (except zero vector).</p><p>Vector addition is defined as follow:</p><hr /><p>Two distinct vectors (a<sub>1</sub>, a<sub>2</sub>, a<sub>3</sub>, … , a<sub>n</sub>) and (b<sub>1</sub>, b<sub>2</sub>, b<sub>3</sub>, … , b<sub>n</sub>) are denoted by <strong>a</strong> and <strong>b</strong>.</p><p><strong>a</strong> + <strong>b</strong> := (a<sub>1</sub> + b<sub>1</sub>, a<sub>2</sub> + b<sub>2</sub>, a<sub>3</sub> + b<sub>3</sub>, … , a<sub>n</sub> + b<sub>n</sub>)</p><hr /><p>This part is very straghtforward.</p><p>Using vector addition, we can find the (To do)</p><h3 id="vector-scalar-multiplication"><a class="markdownIt-Anchor" href="#vector-scalar-multiplication"></a> Vector scalar multiplication</h3><p>However, sometimes, we also want to the multiples of a vector. For example, I know that a car go at (5, 5) km/h, and I think the car is too slow, so that I speed up the car for 10%. Now I need to know the current velocity of the car.</p><p>Vector scalar multiplication:</p><hr /><p>s is a scalar , and (v<sub>1</sub>, v<sub>2</sub>, v<sub>3</sub>, … v<sub>n</sub>) is a vector denoted by <strong>v</strong>.</p><p>s__v__ := (sv<sub>1</sub>, sv<sub>2</sub>, sv<sub>3</sub>, … sv<sub>n</sub>)</p><hr /><p>It is worthnoting that s, v<sub>1</sub>, v<sub>2</sub>, v<sub>3</sub>, … v<sub>n</sub> <span class="katex"><span class="katex-mathml"><math><semantics><mrow><mo>∈</mo><mi mathvariant="double-struck">R</mi></mrow><annotation encoding="application/x-tex">\in \R</annotation></semantics></math></span><span class="katex-html" aria-hidden="true"><span class="base"><span class="strut" style="height:0.5782em;vertical-align:-0.0391em;"></span><span class="mrel">∈</span><span class="mspace" style="margin-right:0.2777777777777778em;"></span></span><span class="base"><span class="strut" style="height:0.68889em;vertical-align:0em;"></span><span class="mord"><span class="mord mathbb">R</span></span></span></span></span> .  When s = 0, s__v__ = <strong>0</strong> , where <strong>v</strong> is any vector, and <strong>0</strong> is the zero vector. In similar way, s__0__ = <strong>0</strong>.</p><p>For convenience, we denote ( -1__v __) as ( -__v __).</p><p>这里不太确定是不是另有深意, 我觉得是为了方便.</p><h3 id="interface-toward-vector-space"><a class="markdownIt-Anchor" href="#interface-toward-vector-space"></a> Interface toward Vector Space</h3><p>Now we can talk about some more exciting contents. :happy:</p><p>First of all, one thing need to declare is that we haven’t defined an operation called substraction. As a matter of fact, we do not need to.</p><p>Let’s examine the properties of the two operations on vector which we defined.</p><table><thead><tr><th>Property</th><th>Name of the property</th></tr></thead><tbody><tr><td>1. ( <strong>u</strong> + <strong>v</strong> ) is a vector has the same dimension as <strong>u</strong> and <strong>v</strong></td><td>Closure under addition</td></tr><tr><td>2. <strong>u</strong> + <strong>v</strong> = <strong>v</strong> + <strong>u</strong></td><td>Communicative property of addition</td></tr><tr><td>3. <strong>u</strong> + <strong>v</strong> + <strong>w</strong> = <strong>u</strong> + ( <strong>v</strong> + <strong>w</strong> )</td><td>Association property of addition</td></tr><tr><td>4. <strong>u</strong> + <strong>0</strong> = <strong>u</strong></td><td>Identity property of addition</td></tr><tr><td>5. <strong>u</strong> + -<strong>u</strong> = <strong>0</strong></td><td>Inverse property of addition</td></tr><tr><td>6. c__u__ is a vector has the same dimension as <strong>u</strong></td><td>Closure under scalar multiplication</td></tr><tr><td>7. c ( <strong>u</strong> + <strong>v</strong> ) = c__u__ + c__v__</td><td>Distributive property</td></tr><tr><td>8. ( c + d ) <strong>u</strong> = c__u__ + d__u__9. cd__u__ = c(d__u__)</td><td>Distributive property</td></tr><tr><td>10. 1__u__ = <strong>u</strong></td><td>Identity property of multiplication</td></tr></tbody></table><p>These properties are very easy to prove for vectors.</p><p>这里稍微逼逼两句, 各种空间啊, 群啊啥的, 让我感觉非常安心, 因为我知道我做了这些操作之后不会蹦出来一个东西我没见错</p><h3 id=""><a class="markdownIt-Anchor" href="#"></a> </h3>]]></content>
    
    
    
    <tags>
      
      <tag>Vector and Matrix</tag>
      
      <tag>Maths</tag>
      
      <tag>Learning Note</tag>
      
      <tag>Quantum Book</tag>
      
    </tags>
    
  </entry>
  
  
  
  <entry>
    <title>数列技巧: 不动点</title>
    <link href="/2020/%E6%95%B0%E5%88%97%E6%8A%80%E5%B7%A7-%E4%B8%8D%E5%8A%A8%E7%82%B9/"/>
    <url>/2020/%E6%95%B0%E5%88%97%E6%8A%80%E5%B7%A7-%E4%B8%8D%E5%8A%A8%E7%82%B9/</url>
    
    <content type="html"><![CDATA[]]></content>
    
    
    
  </entry>
  
  
  
  <entry>
    <title>Vector and Matrix: Mindmap</title>
    <link href="/2020/Vector-and-Matrix-Mindmap/"/>
    <url>/2020/Vector-and-Matrix-Mindmap/</url>
    
    <content type="html"><![CDATA[<h1 id="vector-and-matrix"><a class="markdownIt-Anchor" href="#vector-and-matrix"></a> Vector and Matrix</h1><h3 id="introduction"><a class="markdownIt-Anchor" href="#introduction"></a> Introduction</h3><blockquote><p>Before go to the content, here is a brief introduction talking about the purpose of this post and also a explaination of the form of this serie of posts.</p><p>The serie of the post mainly have three purposes. Firstly, it is a review of Linear algebra for myself. Secondly, I want to give the content of linear algebra a better explaination. And thirdly, it is a trail of the new form “Quantum Book”.</p><p>The whole serie of  posts is writen in the form of “Quantum Book” (I made up the name). Which you can get more information about it at [here](i_will _add_it_later_on).</p></blockquote><h3 id="map"><a class="markdownIt-Anchor" href="#map"></a> Map</h3><p>The map starts here.</p><p>Here will be a picture.</p><ol><li>A Review of Vector</li><li>Matrix operation and Linear equation</li><li>Linear transformation</li><li>Vector Space</li><li>Inner Product Space</li><li>Eigenvalue and Eigenvector</li></ol>]]></content>
    
    
    
    <tags>
      
      <tag>Vector and Matrix</tag>
      
      <tag>Maths</tag>
      
      <tag>Learning Note</tag>
      
      <tag>Quantum Book</tag>
      
    </tags>
    
  </entry>
  
  
  
  <entry>
    <title>建站指南</title>
    <link href="/2020/%E5%BB%BA%E7%AB%99%E6%8C%87%E5%8D%97/"/>
    <url>/2020/%E5%BB%BA%E7%AB%99%E6%8C%87%E5%8D%97/</url>
    
    <content type="html"><![CDATA[<h1 id="建站指南"><a class="markdownIt-Anchor" href="#建站指南"></a> 建站指南</h1><p>这篇文章主要是介绍怎样利用 github 以及 hexo 快速搭建简易的博客站. 同时这也是我的练手文章, 用来熟悉博客站的操作.</p><p>Markdown 的介绍请看 <a href="https://www.markdownguide.org/" target="_blank" rel="noopener">这里</a>.</p><h3 id="github-以及-hexo-的简介"><a class="markdownIt-Anchor" href="#github-以及-hexo-的简介"></a> GitHub 以及 Hexo 的简介</h3><p><a href="github.com">Github</a> 是一个代码托管网站. 你可以在这里下载到很多很好玩的代码, 当然也不只是代码, 比如本篇文章就是托管在 Github 上, 利用 Github Pages 的某种特性发布的. 具体细节我也不清楚…</p><p>Github的核心是一个开源的版本控制系统 Git. Git 的各种操作我们在这里不讨论. 未来我可能会写一篇关于 Git 的学习笔记…</p><p>关于Github 我们如果只是想搭建博客的话不需要了解太多.</p><p>Hexo 是一个快速的博客框架. Hexo 依赖 于Node.js 和 Git. Hexo 可以方便的把markdown文档生成网页, 管理博客, 并且把网页部署到各种网站. <a href="https://hexo.io/zh-cn/docs/index.html" target="_blank" rel="noopener">这里</a>是他的文档.</p><h3 id="github-中的配置"><a class="markdownIt-Anchor" href="#github-中的配置"></a> GitHub 中的配置</h3><p>登录到 Github. 如果没有注册, 我们可以在<a href="https://link.zhihu.com/?target=https%3A//github.com/">这里</a>注册. 之后我们点击 New repository 创建仓库. 这里需要注意的是, 仓库的名字必须是 &lt;user_name&gt;.github.io 其中 &lt;user_name&gt; 是 Github 的 username.</p><h3 id="hexo-的安装"><a class="markdownIt-Anchor" href="#hexo-的安装"></a> Hexo 的安装</h3><p>Hexo 的安装很容易, 但是外那之前, 我们需要先检查是否已经安装了 Hexo 的依赖.</p><p>首先, 我们检查是否安装了 Git, 在命令台输入:</p><p><code>git --version</code></p><p>之后检查 Node.js :</p><p><code>node -v</code></p><p>如果显示了版本即位安装完成.</p><p><a href="https://git-scm.com/" target="_blank" rel="noopener">Git</a> 和  <a href="https://nodejs.org/en/about/" target="_blank" rel="noopener">Node.js</a> 安装的网站. Node.js 安装过程是图形化的, 所以比较容易.</p><h4 id="git-的配置"><a class="markdownIt-Anchor" href="#git-的配置"></a> Git 的配置</h4><p>在Git 网站安装好 Git 之后, 我们需要先配置Git</p><blockquote><p>在安装 Git 的时候可能需要 Xcode 的依赖, 这部分可以上网搜索解决.</p></blockquote><pre class="highlight"><code class="">git config --global user.name &quot;&lt;your_name&gt;&quot;git config --global user.email &quot;&lt;your_email_address&gt;&quot;</code></pre><p>这里的名字和邮箱建议用比较正经的, 因为未来你很有可能继续使用 Git 和你的同事管理版本.</p><p>使用 ssh 我们就不用在部署博客的时候每次都输密码. 我们生成 ssh 密钥连接 Git 和 Github. 使用 ssh-keygen 命令生成 密钥和公钥:</p><pre class="highlight"><code class="">ssh-keygen -t rsa -C &quot;&lt;your_email_address&gt;&quot;</code></pre><p>按照提示创建密码, 或者回车不适用密码. 密码要牢记, 忘了就得重新生成 ssh 密钥对了.</p><p>密钥对存在用户目录的 ~/.ssh 目录下. <code>/Users/&lt;user_name&gt;/.ssh</code>, 其中 &lt;user_name&gt; 是电脑用户的名称.</p><p>我们需要把公钥拷贝到 Github 上. 打开Github_Settings_keys 页面, 粘贴进去就可以了. 这部分参考 <a href="https://help.github.com/cn/github/authenticating-to-github/connecting-to-github-with-ssh" target="_blank" rel="noopener">这里</a></p><p>之后, 我们就可以使用</p><pre class="highlight"><code class="">ssh github@github.com</code></pre><p>命令测试是否正常连接. 正常连接的话会显示 Hi &lt;your name&gt;…</p><h3 id="hexo-的安装-2"><a class="markdownIt-Anchor" href="#hexo-的安装-2"></a> Hexo 的安装</h3><p>现在转移到 Hexo 的安装过程. 在安装好依赖之后, 我们可以一行命令安装npm.</p><p><code>npm install -g hexo-cli</code></p><h3 id="hexo-建站"><a class="markdownIt-Anchor" href="#hexo-建站"></a> Hexo 建站</h3><p>完成 Hexo 的安装之后, 我们需要现在本地准备好我们的网站的所有文档.</p><p>首先我们来到我们想要开始建站的目录, 比如 ~\Document.</p><pre class="highlight"><code class="">hexo init &lt;folder&gt;cd &lt;folder&gt;</code></pre><p>&lt;folder&gt; 填你的博客文件夹的名字 比如 hexo-blog-folder. 做好之后文件夹内的目录应该是这样.</p><pre class="highlight"><code class="">.├── _config.yml├── package.json├── scaffolds├── source|   ├── _drafts|   └── _posts└── themes</code></pre><p>我们的文件已经生成好了. 现在我们需要对站点进行配置.</p><p>我们修改 _config.yml 文档.</p><p>参考 <a href="https://hexo.io/zh-cn/docs/configuration" target="_blank" rel="noopener">这个</a> 网站.</p><p>比较重要需要修改的是 title, subtitle, author, language, theme, 以及deploy.</p><p>值得注意的是,  deploy 部分容易出现问题. 这里提供一个简单的例子.</p><pre class="highlight"><code class="">deploy:     type: git     repo: https://github.com/&lt;your-name&gt;/&lt;your-name&gt;.github.io.git     branch: master</code></pre><p>&lt;your-name&gt; 填你的 Github 用户名.</p><p>这里我们的网站就建好了.</p><p>我们用 <code>hexo server</code> 命令来检查网站搭建进度.</p><h3 id="hexo的常用命令-以及-工作流"><a class="markdownIt-Anchor" href="#hexo的常用命令-以及-工作流"></a> Hexo的常用命令 以及 工作流</h3><p>首先我们介绍几个常用命令:</p><ul><li><code>hexo new [type]&quot;&lt;page_name&gt;&quot;</code><ul><li>new 命令新建一个网页.</li><li>[type] 是文章的种类, 默认是 post 也就是博客, &lt;page_name&gt; 是新建的网页的名字和标题.</li></ul></li><li><code>hexo server</code> 或者简写为 <code>hexo s</code><ul><li>server 命令 在本地预览网页</li></ul></li><li><code>hexo clean</code><ul><li>clean 命令 删除本地生成的网页文档, 防止冲突</li></ul></li><li><code>hexo generate</code> 或者简写为 <code>hexo g</code><ul><li>generate 命令 在本地生成网页文档</li></ul></li><li><code>hexo deploy</code> 或者简写为 <code>hexo d</code><ul><li>deploy 命令 把生成的本地文档部署到云端, 这里就是放到 Github 上.</li></ul></li></ul><p>之后我们介绍工作流, 以写第一篇文章为例</p><p>首先, 使用 <code>hexo new</code> 命令生成一篇md格式的文章模版.</p><p>文章放在 ~\source\__post 目录下. 我们使用markdown 编辑器添加文章的内容. Markdown 的介绍请看 <a href="https://www.markdownguide.org/" target="_blank" rel="noopener">这里</a>.</p><p>之后, 我们就可以用 <code>hexo server</code> 命令来在本地预览文章.</p><p>确认无误之后, 我们可以用 <code>hexo clean</code>,<code>hexo g</code>,<code>hexo d</code>三连大法将文章部署到 Github 上.</p><p>我们通过 &lt;user_name&gt;<a href="http://github.io" target="_blank" rel="noopener">github.io</a> 来访问我们的博客.</p>]]></content>
    
    
    
    <tags>
      
      <tag>学习笔记</tag>
      
    </tags>
    
  </entry>
  
  
  
  
</search>
